[1,0,0,[["dragonBones.DragonBonesAsset",["_name","_dragonBonesJson"],1]],[[0,0,1,3]],[[0,"restart_ske","{\"frameRate\":60,\"name\":\"restart\",\"version\":\"5.5\",\"compatibleVersion\":\"5.5\",\"armature\":[{\"type\":\"Armature\",\"frameRate\":60,\"name\":\"Armature\",\"aabb\":{\"x\":-84.5,\"y\":-84.5,\"width\":169,\"height\":212.33},\"bone\":[{\"name\":\"root\"},{\"name\":\"刷新\",\"parent\":\"root\"}],\"slot\":[{\"name\":\"RESTART\",\"parent\":\"刷新\"},{\"name\":\"2\",\"parent\":\"刷新\"},{\"name\":\"刷新\",\"parent\":\"刷新\"}],\"skin\":[{\"slot\":[{\"name\":\"刷新\",\"display\":[{\"name\":\"刷新\"}]},{\"name\":\"2\",\"display\":[{\"type\":\"mesh\",\"name\":\"2\",\"width\":169,\"height\":169,\"vertices\":[-84.5,-84.5,84.5,-84.5,-84.5,84.5,84.5,84.5],\"uvs\":[0,0,1,0,0,1,1,1],\"triangles\":[1,0,3,0,2,3],\"edges\":[0,1,1,3,3,2,2,0],\"userEdges\":[]}]},{\"name\":\"RESTART\",\"display\":[{\"name\":\"RESTART\",\"transform\":{\"y\":99.33}}]}]}],\"animation\":[{\"duration\":18,\"playTimes\":0,\"name\":\"restart\",\"slot\":[{\"name\":\"刷新\",\"displayFrame\":[{\"duration\":8,\"value\":-1},{\"duration\":10}],\"colorFrame\":[{\"duration\":8},{\"duration\":10,\"tweenEasing\":0,\"value\":{\"aM\":0}},{\"duration\":0}]},{\"name\":\"2\",\"displayFrame\":[{\"duration\":3,\"value\":-1},{\"duration\":15}],\"colorFrame\":[{\"duration\":8},{\"duration\":10,\"tweenEasing\":0},{\"duration\":0,\"value\":{\"aM\":0}}]},{\"name\":\"RESTART\",\"displayFrame\":[{\"duration\":8,\"value\":-1},{\"duration\":10}],\"colorFrame\":[{\"duration\":8},{\"duration\":10,\"tweenEasing\":0,\"value\":{\"aM\":0}},{\"duration\":0}]}],\"ffd\":[{\"name\":\"2\",\"slot\":\"2\",\"frame\":[{\"duration\":3},{\"duration\":5,\"tweenEasing\":0,\"offset\":1,\"vertices\":[49.7,0,49.7,0,-60.7,0,-60.7]},{\"duration\":10}]}]}],\"defaultActions\":[{\"gotoAndPlay\":\"restart\"}]}]}"]],0,0,[],[],[]]